pulumi_artifactory/__init__.py
pulumi_artifactory/_inputs.py
pulumi_artifactory/_utilities.py
pulumi_artifactory/alpine_repository.py
pulumi_artifactory/anonymous_user.py
pulumi_artifactory/api_key.py
pulumi_artifactory/archive_policy.py
pulumi_artifactory/artifact.py
pulumi_artifactory/artifact_custom_webhook.py
pulumi_artifactory/artifact_lifecycle_custom_webhook.py
pulumi_artifactory/artifact_lifecycle_webhook.py
pulumi_artifactory/artifact_property_custom_webhook.py
pulumi_artifactory/artifact_property_webhook.py
pulumi_artifactory/artifact_webhook.py
pulumi_artifactory/artifactory_release_bundle_custom_webhook.py
pulumi_artifactory/artifactory_release_bundle_webhook.py
pulumi_artifactory/backup.py
pulumi_artifactory/build_custom_webhook.py
pulumi_artifactory/build_webhook.py
pulumi_artifactory/certificate.py
pulumi_artifactory/debian_repository.py
pulumi_artifactory/destination_custom_webhook.py
pulumi_artifactory/destination_webhook.py
pulumi_artifactory/distribution_custom_webhook.py
pulumi_artifactory/distribution_public_key.py
pulumi_artifactory/distribution_webhook.py
pulumi_artifactory/docker_custom_webhook.py
pulumi_artifactory/docker_v1_repository.py
pulumi_artifactory/docker_v2_repository.py
pulumi_artifactory/docker_webhook.py
pulumi_artifactory/federated_alpine_repository.py
pulumi_artifactory/federated_ansible_repository.py
pulumi_artifactory/federated_bower_repository.py
pulumi_artifactory/federated_cargo_repository.py
pulumi_artifactory/federated_chef_repository.py
pulumi_artifactory/federated_cocoapods_repository.py
pulumi_artifactory/federated_composer_repository.py
pulumi_artifactory/federated_conan_repository.py
pulumi_artifactory/federated_conda_repository.py
pulumi_artifactory/federated_cran_repository.py
pulumi_artifactory/federated_debian_repository.py
pulumi_artifactory/federated_docker_repository.py
pulumi_artifactory/federated_docker_v1_repository.py
pulumi_artifactory/federated_docker_v2_repository.py
pulumi_artifactory-8.10.0.dist-info/METADATA
pulumi_artifactory-8.10.0.dist-info/WHEEL
pulumi_artifactory-8.10.0.dist-info/top_level.txt
pulumi_artifactory-8.10.0.dist-info/RECORD
